{"id":"d07234c233e8","content":"There's a version of \"setting up Next.js\" that takes thirty seconds: run create-next-app, done. And for a weekend project, that's genuinely all you need. But we're building a SaaS meant to live for years, inside a monorepo, sharing types with a backend. The choices you make in the first hour here quietly shape how the next hundred hours feel.\n\nSo this isn't a \"run this command\" article. It's the handful of setup decisions that actually matter, and the ones people agonize over that don't.\n\nThis is part three of the Full Stack SaaS Masterclass, continuing from the Turborepo monorepo we set up last time. The Next.js app lives in apps/web.\n\nApp Router or Pages Router?\n\nThis is the first fork, and I'll give you a straight answer: for a new project in 2023, use the App Router. The Pages Router isn't bad. It's stable, and a lot of great apps run on it. But the App Router is where React and Next are clearly heading, and starting a multi-year project on the path that's being deprioritized is borrowing trouble.\n\nThe App Router's real advantage for a SaaS is Server Components. Your dashboard can fetch data on the server, render it to HTML, and ship less JavaScript to the browser. For an app with a lot of data-heavy pages, that's faster loads and better SEO on your marketing pages, more or less for free.\n\nThere's a learning curve. Server Components versus Client Components trips everyone up at first. I'll cover that properly in the React series later. For now: it's worth the curve.\n\nThe setup that matters\n\nInside apps/web, here's what I actually configure before writing any features.\n\nTypeScript, strict. Non-negotiable. Turn on strict mode in tsconfig.json from the very first file. Retrofitting strictness onto a codebase that grew up loose is miserable. I've done it: it's weeks of any whack-a-mole. Pay the small tax now.\n\nPath aliases. Set up @/ to point at your source root so imports stay readable as the app grows.\n\n// tsconfig.json\n{\n\"compilerOptions\": {\n\"strict\": true,\n\"baseUrl\": \".\",\n\"paths\": {\n\"@/*\": [\"./src/*\"]\n}\n}\n}\n\nEnter fullscreen mode\n\nExit fullscreen mode\n\nThe difference this makes six months in:\n\n// without aliases, from a deeply nested file\nimport { Button } from '../../../../components/ui/Button';\n// with aliases, from anywhere\nimport { Button } from '@/components/ui/Button';\n\nEnter fullscreen mode\n\nExit fullscreen mode\n\nThat second version doesn't break when you move the file. The first one does, and you won't notice until runtime.\n\nConsume the shared types. This is the monorepo paying off. Import the User type from the shared package instead of redefining it:\n\nimport type { User } from '@my-saas/types';\nasync function getProfile(): Promise<User> {\nconst res = await fetch(`${process.env.API_URL}/me`);\nreturn res.json();\n}\n\nEnter fullscreen mode\n\nExit fullscreen mode\n\nNow if the backend changes the User shape, this file won't compile until you deal with it. That's the safety net we built the monorepo for, doing its job on the frontend.\n\nTailwind for styling. An opinion, but a well-worn one. For a SaaS you'll build a lot of custom UI, and Tailwind lets you style without inventing a naming system or context-switching to CSS files. If you or your team genuinely prefer CSS Modules or styled-components, that's a fine choice too. This is one of those reversible decisions not worth a war over.\n\nA sane folder structure\n\nPeople burn absurd amounts of time on folder structure. Here's one that works and that you can stop thinking about:\n\napps/web/src/\n├── app/ # App Router routes\n├── components/\n│ ├── ui/ # dumb, reusable primitives (Button, Input)\n│ └── features/ # feature-specific components\n├── lib/ # helpers, API client, utilities\n├── hooks/ # custom React hooks\n└── styles/ # global css, tailwind entry\n\nEnter fullscreen mode\n\nExit fullscreen mode\n\nThe one distinction I'd insist on is ui versus features. ui holds generic primitives that know nothing about your app. A Button doesn't care whether it's on a billing page. features holds components that do: a BillingSummary that knows about invoices. Keeping those separate stops your reusable primitives from slowly getting tangled up in business logic, which is how component libraries rot.\n\nEverything else, don't overthink. You can always move a file. You cannot always undo a strict: false codebase.\n\nWhat not to install yet\n\nThe instinct on day one is to add every library you might need. Resist it. You don't yet know if you need a state management library. Server Components and React's built-in state cover more than they used to. You don't need a data-fetching library until you have data to fetch. You don't need a form library until you have a form.\n\nEach dependency is a thing to learn, update, and occasionally get burned by. Add them when a real need shows up, not in anticipation. The create-next-app default plus TypeScript, Tailwind, and your shared types is a complete enough starting point to build real features on.\n\nNext in the series, we set up the other side: the NestJS backend that serves those shared types, inside the same monorepo.\n\nKey takeaways\n\n• For a new multi-year project, start on the App Router. It's where Next.js is heading, and Server Components cut shipped JavaScript.\n\n• Turn on TypeScript strict from the first file; retrofitting it later is painful.\n\n• Set up @/ path aliases so imports stay stable when you move files.\n\n• Import shared types from the monorepo package so frontend and backend can't drift.\n\n• Keep reusable ui primitives separate from features components, and don't install libraries until a real need appears.\n\nFAQ\n\nShould I use the App Router or Pages Router for a new Next.js app?\n\nUse the App Router for new projects. It's the direction Next.js is investing in, and Server Components reduce client-side JavaScript and improve SEO. The Pages Router still works but is the legacy path.\n\nWhy enable TypeScript strict mode from the start?\n\nStrict mode catches whole categories of bugs at compile time. Adding it to an existing loose codebase means fixing a flood of errors all at once, so it's far cheaper to start strict.\n\nWhat folder structure should a Next.js SaaS use?\n\nA simple one: app for routes, components/ui for generic primitives, components/features for app-specific components, plus lib, hooks, and styles. Keep reusable primitives free of business logic.\n\nDo I need a state management library like Redux?\n\nNot to start. React's built-in state and Server Components handle a lot now. Add a state library only when you hit genuine shared-state complexity that local state can't handle cleanly.\n\nHow do I share types between my Next.js app and backend?\n\nPut the types in a shared monorepo package and import them on both sides. Any change to a type then forces both apps to update, preventing silent mismatches.\n\nFurther reading\n\n• Previous: Setting Up a Monorepo with Turborepo\n\n• Next: Setting Up NestJS the Right Way\n\n• Start of series: Choosing the Right Tech Stack for Your SaaS\n\nAbout the Author\n\nHi, I'm Aman Singh — Senior Full Stack Engineer specializing in scalable SaaS products, distributed systems, cloud architecture, and AI-powered applications.\n\nI write about System Design, Full Stack Engineering, Distributed Systems, Redis, PostgreSQL, AWS, Node.js, and NestJS.\n\n• Portfolio: https://amanksingh.com\n\n• GitHub: https://github.com/amansingh1501\n\n• Product: https://vowerole.com\n\n• Email: aman97aman@gmail.com"}